rat/__init__.py
rat/rat_basin.py
rat/run_rat.py
rat/cli/rat_cli.py
rat/cli/rat_init_config.py
rat/cli/rat_test_config.py
rat/cli/rat_test_verify.py
rat/core/run_altimetry.py
rat/core/run_metsim.py
rat/core/run_postprocessing.py
rat/core/run_routing.py
rat/core/run_sarea.py
rat/core/run_vic.py
rat/core/sarea/TMS.py
rat/core/sarea/bot_filter.py
rat/core/sarea/multisensor_ssc_integrator.py
rat/core/sarea/sarea_cli_l5.py
rat/core/sarea/sarea_cli_l7.py
rat/core/sarea/sarea_cli_l8.py
rat/core/sarea/sarea_cli_l9.py
rat/core/sarea/sarea_cli_s2.py
rat/core/sarea/sarea_cli_sar.py
rat/data_processing/__init__.py
rat/data_processing/altimetry.py
rat/data_processing/metsim_input_processing.py
rat/data_processing/newdata.py
rat/data_processing/newdata_low_latency.py
rat/ee_utils/__init__.py
rat/ee_utils/ee_aec_file_creator.py
rat/ee_utils/ee_config.py
rat/ee_utils/ee_utils.py
rat/plugins/forecasting/forecast_basin.py
rat/plugins/forecasting/forecasting.py
rat/plugins/resorr/data_prep.py
rat/plugins/resorr/network.py
rat/plugins/resorr/reservoir.py
rat/plugins/resorr/runResorr.py
rat/toolbox/MiscUtil.py
rat/toolbox/__init__.py
rat/toolbox/config.py
rat/toolbox/data_transform.py
rat/toolbox/visualize.py
rat/utils/__init__.py
rat/utils/clean.py
rat/utils/convert_to_final_outputs.py
rat/utils/files_creator.py
rat/utils/logging.py
rat/utils/metsim_param_reader.py
rat/utils/route_param_reader.py
rat/utils/run_command.py
rat/utils/science.py
rat/utils/utils.py
rat/utils/vic_init_state_finder.py
rat/utils/vic_param_reader.py
rat-3.0.18.dist-info/licenses/LICENSE
rat-3.0.18.dist-info/METADATA
rat-3.0.18.dist-info/WHEEL
rat-3.0.18.dist-info/top_level.txt
rat-3.0.18.dist-info/RECORD
