Metadata-Version: 2.4
Name: rat
Version: 3.0.18
Summary: Resevoir Monitoring using Satellite Remote Sensing
Author-email: Pritam Das <pdas47@uw.edu>, Sanchit Minocha <msanchit@uw.edu>
License:                     GNU GENERAL PUBLIC LICENSE
Project-URL: Homepage, https://github.com/UW-SASWE/RAT
Project-URL: Bug Tracker, https://github.com/UW-SASWE/RAT/issues
Classifier: Programming Language :: Python :: 3
Classifier: License :: OSI Approved :: MIT License
Requires-Python: >=3.6
License-File: LICENSE
Requires-Dist: rasterio
Requires-Dist: xarray
Requires-Dist: geopandas
Requires-Dist: rioxarray
Requires-Dist: earthengine-api
Requires-Dist: pandas
Requires-Dist: numpy
Requires-Dist: netcdf4
Requires-Dist: dask
Requires-Dist: scipy
Requires-Dist: scikit-learn
Requires-Dist: ruamel-yaml
Requires-Dist: PyYAML
Requires-Dist: gdown
Requires-Dist: geonetworkx
Requires-Dist: cfgrib
Dynamic: license-file
